[
    {
        "name": "Системаҳои автоматонидашудаи коркарди маълумот ва идоракунӣ",
        "rasm": "sai.jpg",
        "id": 0,
        "id_fakultet": 0
    },
    {
        "name": "Шабакаҳои алоқа ва тақсими иттилоот",
        "rasm": "svjas.jpg",
        "id": 1,
        "id_fakultet": 0
    },
    {
        "name": "Информатика ва техникаи ҳисоббарор",
        "rasm": "informat.jpg",
        "id": 2,
        "id_fakultet": 0
    },
    {
        "name": "Технологияҳои иттилоотӣ ва ҳифзи маълумот",
        "rasm": "hifzi_malumot.png",
        "id": 3,
        "id_fakultet": 0
    },
    {
        "name": "Математикаи олӣ",
        "rasm": "vishi_mat.jpg",
        "id": 4,
        "id_fakultet": 0
    },
    {
        "name": "Фанҳои Ҷомеашиносӣ",
        "rasm": "jomeashinosi.jpg",
        "id": 5,
        "id_fakultet": 0
    },
    {
        "name": "Электротаъминкунӣ",
        "rasm": "pit1.jpg",
        "id": 6,
        "id_fakultet": 1
    },
    {
        "name": "Ҳаракатдиҳандаҳои автоматикунони-дашудаи электрӣ ва мошинҳои электрӣ",
        "rasm": "elekt.jpg",
        "id": 7,
        "id_fakultet": 1
    },
    {
        "name": "Нерӯгоҳҳои электрикӣ",
        "rasm": "nerugoh.jpg",
        "id": 8,
        "id_fakultet": 1
    },
    {
        "name": "Асосҳои назариявии радио ва электротехника",
        "rasm": "asosho.jpg",
        "id": 9,
        "id_fakultet": 1
    },
    {
        "name": "Техникаи гармо ва таҷҳизотҳои гармидиҳӣ",
        "rasm": "tekhnikagarmo.jpg",
        "id": 10,
        "id_fakultet": 1
    },
    {
        "name": "Физика",
        "rasm": "fisika.jpg",
        "id": 11,
        "id_fakultet": 1
    },
    {
        "name": "Иқтисодиёт ва идора дар истеҳсолот",
        "rasm": "iqtisodidora.jpg",
        "id": 12,
        "id_fakultet": 1
    },
    {
        "name": "Ҳимояи релеӣ ва автоматика",
        "rasm": "himoyai rele.jpg",
        "id": 13,
        "id_fakultet": 1
    },
    {
        "name": "Истифодабарии нақлиёти автомобилӣ",
        "rasm": "ist naqliyot.jpg",
        "id": 14,
        "id_fakultet": 2
    },
    {
        "name": "Таркиби ҳаракаткунандаи роҳи оҳан",
        "rasm": "rohiohan.jpg",
        "id": 15,
        "id_fakultet": 2
    },
    {
        "name": "Истифодабарии техникии нақлиёти ҳавоӣ",
        "rasm": "naqhavoi.jpg",
        "id": 16,
        "id_fakultet": 2
    },
    {
        "name": "Ҷузъҳои мошин ва мошинҳои сохтмонию роҳсозӣ",
        "rasm": "moshinairoh.jpg",
        "id": 17,
        "id_fakultet": 2
    },
    {
        "name": "Механикаи назариявӣ ва муқовимати мавод",
        "rasm": "mechanikanazariya.jpg",
        "id": 18,
        "id_fakultet": 2
    },
    {
        "name": "Технологияи коркарди нахҳои табиӣ",
        "rasm": "nakhhotabii.jpg",
        "id": 19,
        "id_fakultet": 3
    },
    {
        "name": "Технологияи мошинсозӣ, дастгоҳҳо ва асбобҳои металлбурӣ",
        "rasm": "tekhnologiyamoshin.jpg",
        "id": 20,
        "id_fakultet": 3
    },
    {
        "name": "Бехатарии фаъолияти инсон ва экология",
        "rasm": "faoliyatinsonekologiya.jpg",
        "id": 21,
        "id_fakultet": 3
    },
    {
        "name": "Масолеҳшиносӣ , мошинҳо ва  таҷҳизотҳои металлургӣ",
        "rasm": "masolehimoshin.jpg",
        "id": 22,
        "id_fakultet": 3
    },
    {
        "name": "Технологияи мошинҳо ва таҷҳизотхои истеҳсолоти полигрофӣ",
        "rasm": "tekhmoshinpolig.jpg",
        "id": 23,
        "id_fakultet": 3
    },
    {
        "name": "Металлургия",
        "rasm": "metalurgiya.jpg",
        "id": 24,
        "id_fakultet": 3
    },
    {
        "name": "Технологияи истеҳсолоти химиявӣ",
        "rasm": "tekhistkhimiya.jpg",
        "id": 25,
        "id_fakultet": 3
    },
    {
        "name": "Менеҷменти истеҳсолӣ» ",
        "rasm": "menegisteh.jpg",
        "id": 26,
        "id_fakultet": 3
    },
    {
        "name": "Химияи умумӣ ва ғайриорганикӣ",
        "rasm": "khimiya.jpg",
        "id": 27,
        "id_fakultet": 3
    },
    {
        "name": "Ихтисосҳои равияи мошинсозӣ",
        "rasm": "moshinsozi.jpg",
        "id": 28,
        "id_fakultet": 4
    },
    {
        "name": "Ихтисосҳои равияи сохтмонӣ",
        "rasm": "sokhtmoni.jpg",
        "id": 29,
        "id_fakultet": 4
    },
    {
        "name": "Ихтисосҳои равияи меъморӣ:",
        "rasm": "arkhitektur.jpg",
        "id": 30,
        "id_fakultet": 4
    },
    {
        "name": "Ихтисосҳои равияи энергетикӣ",
        "rasm": "raviyaienergetiki.jpg",
        "id": 31,
        "id_fakultet": 4
    },
    {
        "name": "Ихтисосҳои равияи нақлиёт",
        "rasm": "istnaqliyot.jpg",
        "id": 32,
        "id_fakultet": 4
    },
    {
        "name": "Ташкили интиқол ва идора дар нақлиёт",
        "rasm": "tashintnaq.jpg",
        "id": 33,
        "id_fakultet": 5
    },
    {
        "name": "Сохтмони роҳҳо, иншоот ва коммуникатсияҳои нақлиётӣ",
        "rasm": "sokhtmonrohho.jpg",
        "id": 34,
        "id_fakultet": 5
    },
    {
        "name": "Иқтисодиёт ва логистикаи нақлиётӣ",
        "rasm": "logistnaq.jpg",
        "id": 35,
        "id_fakultet": 5
    },
    {
        "name": "Забонҳо",
        "rasm": "zabon.jpg",
        "id": 36,
        "id_fakultet": 5
    },
    {
        "name": "Тарбияи ҷисмонӣ",
        "rasm": "tarbiyachis.jpg",
        "id": 37,
        "id_fakultet": 5
    },
    {
        
    }
]